glfw/__init__.pyi
glfw_types-1.0.1.dist-info/LICENSE.txt
glfw_types-1.0.1.dist-info/METADATA
glfw_types-1.0.1.dist-info/WHEEL
glfw_types-1.0.1.dist-info/top_level.txt
glfw_types-1.0.1.dist-info/RECORD
